{
  "category": {
    "id": 17,
    "title": "家庭纠纷"
  },
  "query": {
    "q": "家庭纠纷",
    "part": "snippet",
    "order": "rating"
  },
  "page": {
    "page_index": 2,
    "max_results": 50
  },
  "items": [
    {
      "kind": "youtube#searchResult",
      "etag": "CRA8XkEaNTRVSIBtJnnxgpXAld0",
      "id": {
        "kind": "youtube#video",
        "videoId": "Klz9a4Em-DE"
      },
      "snippet": {
        "publishedAt": "2025-11-18T12:00:48Z",
        "channelId": "UCuiqig0xIFhexG73ABx-GbA",
        "title": "一口气看完爽文小说推荐高质量家庭纠纷完结文 #一口气系列 #完结文 #拯救文荒小说 #有声小说 #元宝图图",
        "description": "一口气看完爽文小说推荐高质量家庭纠纷完结文#一口气系列#完结文#拯救文荒小说#有声小说#元宝图图.",
        "thumbnails": {
          "default": {
            "url": "https://i.ytimg.com/vi/Klz9a4Em-DE/default.jpg",
            "width": 120,
            "height": 90
          },
          "medium": {
            "url": "https://i.ytimg.com/vi/Klz9a4Em-DE/mqdefault.jpg",
            "width": 320,
            "height": 180
          },
          "high": {
            "url": "https://i.ytimg.com/vi/Klz9a4Em-DE/hqdefault.jpg",
            "width": 480,
            "height": 360
          }
        },
        "channelTitle": "元宝图图",
        "liveBroadcastContent": "none",
        "publishTime": "2025-11-18T12:00:48Z"
      }
    },
    {
      "kind": "youtube#searchResult",
      "etag": "1E_ouH3C7-VJ_kWq6HBIZw6IYsc",
      "id": {
        "kind": "youtube#video",
        "videoId": "OePJoIlDyn4"
      },
      "snippet": {
        "publishedAt": "2025-10-21T03:45:03Z",
        "channelId": "UC1B1lQEMt-H25hUzEb59OZQ",
        "title": "一口气看完爽文小说推荐高质量家庭纠纷完结文",
        "description": "点点订阅，一夜暴富#小说#完结文#动漫#动画.",
        "thumbnails": {
          "default": {
            "url": "https://i.ytimg.com/vi/OePJoIlDyn4/default.jpg",
            "width": 120,
            "height": 90
          },
          "medium": {
            "url": "https://i.ytimg.com/vi/OePJoIlDyn4/mqdefault.jpg",
            "width": 320,
            "height": 180
          },
          "high": {
            "url": "https://i.ytimg.com/vi/OePJoIlDyn4/hqdefault.jpg",
            "width": 480,
            "height": 360
          }
        },
        "channelTitle": "明月动漫 Moonlight Anime",
        "liveBroadcastContent": "none",
        "publishTime": "2025-10-21T03:45:03Z"
      }
    },
    {
      "kind": "youtube#searchResult",
      "etag": "EsA1tAqnVwz_Fir4dQ-vzvBGg3I",
      "id": {
        "kind": "youtube#video",
        "videoId": "q3a9BEWvqqk"
      },
      "snippet": {
        "publishedAt": "2025-11-18T12:01:51Z",
        "channelId": "UCuiqig0xIFhexG73ABx-GbA",
        "title": "一口气看完爽文小说推荐高质量家庭纠纷完结文 #一口气系列 #完结文 #拯救文荒小说 #有声小说 #元宝图图",
        "description": "一口气看完爽文小说推荐高质量家庭纠纷完结文#一口气系列#完结文#拯救文荒小说#有声小说#元宝图图.",
        "thumbnails": {
          "default": {
            "url": "https://i.ytimg.com/vi/q3a9BEWvqqk/default.jpg",
            "width": 120,
            "height": 90
          },
          "medium": {
            "url": "https://i.ytimg.com/vi/q3a9BEWvqqk/mqdefault.jpg",
            "width": 320,
            "height": 180
          },
          "high": {
            "url": "https://i.ytimg.com/vi/q3a9BEWvqqk/hqdefault.jpg",
            "width": 480,
            "height": 360
          }
        },
        "channelTitle": "元宝图图",
        "liveBroadcastContent": "none",
        "publishTime": "2025-11-18T12:01:51Z"
      }
    },
    {
      "kind": "youtube#searchResult",
      "etag": "FqiqRWyny72NxsZyMaAIsz17lTg",
      "id": {
        "kind": "youtube#video",
        "videoId": "dks9PpqMYw0"
      },
      "snippet": {
        "publishedAt": "2025-10-23T02:53:57Z",
        "channelId": "UC1B1lQEMt-H25hUzEb59OZQ",
        "title": "一口气看完爽文小说推荐高质量家庭纠纷完结文2",
        "description": "点点订阅，一夜暴富#小说#完结文#动漫#动画.",
        "thumbnails": {
          "default": {
            "url": "https://i.ytimg.com/vi/dks9PpqMYw0/default.jpg",
            "width": 120,
            "height": 90
          },
          "medium": {
            "url": "https://i.ytimg.com/vi/dks9PpqMYw0/mqdefault.jpg",
            "width": 320,
            "height": 180
          },
          "high": {
            "url": "https://i.ytimg.com/vi/dks9PpqMYw0/hqdefault.jpg",
            "width": 480,
            "height": 360
          }
        },
        "channelTitle": "明月动漫 Moonlight Anime",
        "liveBroadcastContent": "none",
        "publishTime": "2025-10-23T02:53:57Z"
      }
    },
    {
      "kind": "youtube#searchResult",
      "etag": "jgDsf8mK7wC7MAR6F92joQvMD7Y",
      "id": {
        "kind": "youtube#video",
        "videoId": "4a7zVdWC0VE"
      },
      "snippet": {
        "publishedAt": "2025-11-16T12:00:20Z",
        "channelId": "UCuiqig0xIFhexG73ABx-GbA",
        "title": "一口气看完爽文小说推荐高质量家庭纠纷完结文 #一口气系列 #完结文 #拯救文荒小说 #睡前小故事 #元宝图图",
        "description": "一口气看完爽文小说推荐高质量家庭纠纷完结文#一口气系列#完结文#拯救文荒小说#睡前小故事#元宝图图.",
        "thumbnails": {
          "default": {
            "url": "https://i.ytimg.com/vi/4a7zVdWC0VE/default.jpg",
            "width": 120,
            "height": 90
          },
          "medium": {
            "url": "https://i.ytimg.com/vi/4a7zVdWC0VE/mqdefault.jpg",
            "width": 320,
            "height": 180
          },
          "high": {
            "url": "https://i.ytimg.com/vi/4a7zVdWC0VE/hqdefault.jpg",
            "width": 480,
            "height": 360
          }
        },
        "channelTitle": "元宝图图",
        "liveBroadcastContent": "none",
        "publishTime": "2025-11-16T12:00:20Z"
      }
    },
    {
      "kind": "youtube#searchResult",
      "etag": "xzTHi_bteUh8wd74rdZRVf-L408",
      "id": {
        "kind": "youtube#video",
        "videoId": "EBucxii4HUk"
      },
      "snippet": {
        "publishedAt": "2025-11-16T12:00:23Z",
        "channelId": "UCuiqig0xIFhexG73ABx-GbA",
        "title": "一口气看完爽文小说推荐高质量家庭纠纷完结文 #一口气系列 #完结文 #拯救文荒小说 #睡前小故事 #元宝图图",
        "description": "一口气看完爽文小说推荐高质量家庭纠纷完结文#一口气系列#完结文#拯救文荒小说#睡前小故事#元宝图图.",
        "thumbnails": {
          "default": {
            "url": "https://i.ytimg.com/vi/EBucxii4HUk/default.jpg",
            "width": 120,
            "height": 90
          },
          "medium": {
            "url": "https://i.ytimg.com/vi/EBucxii4HUk/mqdefault.jpg",
            "width": 320,
            "height": 180
          },
          "high": {
            "url": "https://i.ytimg.com/vi/EBucxii4HUk/hqdefault.jpg",
            "width": 480,
            "height": 360
          }
        },
        "channelTitle": "元宝图图",
        "liveBroadcastContent": "none",
        "publishTime": "2025-11-16T12:00:23Z"
      }
    },
    {
      "kind": "youtube#searchResult",
      "etag": "jKzKQEfbLj7FXQws90lE4rPVNac",
      "id": {
        "kind": "youtube#video",
        "videoId": "t27C6UQRyUY"
      },
      "snippet": {
        "publishedAt": "2025-11-22T12:01:51Z",
        "channelId": "UCuiqig0xIFhexG73ABx-GbA",
        "title": "一口气看完高质量小说推荐家庭纠纷完结文推荐远离渣男 #一口气系列 #完结文配享太庙 #拯救文荒小说 #有声小说 #元宝图图",
        "description": "一口气看完高质量小说推荐家庭纠纷完结文推荐远离渣男#一口气系列#完结文配享太庙#拯救文荒小说#有声小说#元宝图图.",
        "thumbnails": {
          "default": {
            "url": "https://i.ytimg.com/vi/t27C6UQRyUY/default.jpg",
            "width": 120,
            "height": 90
          },
          "medium": {
            "url": "https://i.ytimg.com/vi/t27C6UQRyUY/mqdefault.jpg",
            "width": 320,
            "height": 180
          },
          "high": {
            "url": "https://i.ytimg.com/vi/t27C6UQRyUY/hqdefault.jpg",
            "width": 480,
            "height": 360
          }
        },
        "channelTitle": "元宝图图",
        "liveBroadcastContent": "none",
        "publishTime": "2025-11-22T12:01:51Z"
      }
    },
    {
      "kind": "youtube#searchResult",
      "etag": "A6eIYOxN5gjULNxACRY2ta0L1Hk",
      "id": {
        "kind": "youtube#video",
        "videoId": "PzySSaM5u9o"
      },
      "snippet": {
        "publishedAt": "2025-10-19T09:41:15Z",
        "channelId": "UC1B1lQEMt-H25hUzEb59OZQ",
        "title": "一口气看完爽文小说推荐高质量家庭纠纷完结文",
        "description": "一口气看完爽文小说推荐高质量家庭纠纷完结文.",
        "thumbnails": {
          "default": {
            "url": "https://i.ytimg.com/vi/PzySSaM5u9o/default.jpg",
            "width": 120,
            "height": 90
          },
          "medium": {
            "url": "https://i.ytimg.com/vi/PzySSaM5u9o/mqdefault.jpg",
            "width": 320,
            "height": 180
          },
          "high": {
            "url": "https://i.ytimg.com/vi/PzySSaM5u9o/hqdefault.jpg",
            "width": 480,
            "height": 360
          }
        },
        "channelTitle": "明月动漫 Moonlight Anime",
        "liveBroadcastContent": "none",
        "publishTime": "2025-10-19T09:41:15Z"
      }
    },
    {
      "kind": "youtube#searchResult",
      "etag": "xeIsVbCR-9DAU7NBxzRA6NkxQLo",
      "id": {
        "kind": "youtube#video",
        "videoId": "Gg7s166flR4"
      },
      "snippet": {
        "publishedAt": "2025-10-14T09:56:59Z",
        "channelId": "UC1B1lQEMt-H25hUzEb59OZQ",
        "title": "一口气看完爽文小说推荐高质量家庭纠纷完结文",
        "description": "",
        "thumbnails": {
          "default": {
            "url": "https://i.ytimg.com/vi/Gg7s166flR4/default.jpg",
            "width": 120,
            "height": 90
          },
          "medium": {
            "url": "https://i.ytimg.com/vi/Gg7s166flR4/mqdefault.jpg",
            "width": 320,
            "height": 180
          },
          "high": {
            "url": "https://i.ytimg.com/vi/Gg7s166flR4/hqdefault.jpg",
            "width": 480,
            "height": 360
          }
        },
        "channelTitle": "明月动漫 Moonlight Anime",
        "liveBroadcastContent": "none",
        "publishTime": "2025-10-14T09:56:59Z"
      }
    },
    {
      "kind": "youtube#searchResult",
      "etag": "QB462W8evFIvCmlgAxOKk7sa3MU",
      "id": {
        "kind": "youtube#video",
        "videoId": "bKrEr8BKl_w"
      },
      "snippet": {
        "publishedAt": "2025-10-22T06:22:16Z",
        "channelId": "UC1B1lQEMt-H25hUzEb59OZQ",
        "title": "一口气看完爽文小说推荐高质量家庭纠纷完结文",
        "description": "点点订阅，一夜暴富#小说#完结文#动漫#动画.",
        "thumbnails": {
          "default": {
            "url": "https://i.ytimg.com/vi/bKrEr8BKl_w/default.jpg",
            "width": 120,
            "height": 90
          },
          "medium": {
            "url": "https://i.ytimg.com/vi/bKrEr8BKl_w/mqdefault.jpg",
            "width": 320,
            "height": 180
          },
          "high": {
            "url": "https://i.ytimg.com/vi/bKrEr8BKl_w/hqdefault.jpg",
            "width": 480,
            "height": 360
          }
        },
        "channelTitle": "明月动漫 Moonlight Anime",
        "liveBroadcastContent": "none",
        "publishTime": "2025-10-22T06:22:16Z"
      }
    },
    {
      "kind": "youtube#searchResult",
      "etag": "Ax67jSc7L6n92-J2ANdzRAWPbgw",
      "id": {
        "kind": "youtube#video",
        "videoId": "msmlSzJLB-4"
      },
      "snippet": {
        "publishedAt": "2025-10-08T08:16:11Z",
        "channelId": "UCevXE1zfgqp8AXPZIaqndmQ",
        "title": "重生复仇爽文小说一口气看完家庭纠纷大女主手撕渣男女频文免费看",
        "description": "",
        "thumbnails": {
          "default": {
            "url": "https://i.ytimg.com/vi/msmlSzJLB-4/default.jpg",
            "width": 120,
            "height": 90
          },
          "medium": {
            "url": "https://i.ytimg.com/vi/msmlSzJLB-4/mqdefault.jpg",
            "width": 320,
            "height": 180
          },
          "high": {
            "url": "https://i.ytimg.com/vi/msmlSzJLB-4/hqdefault.jpg",
            "width": 480,
            "height": 360
          }
        },
        "channelTitle": "如烟大帝",
        "liveBroadcastContent": "none",
        "publishTime": "2025-10-08T08:16:11Z"
      }
    },
    {
      "kind": "youtube#searchResult",
      "etag": "eZxWLbhguVFNtM60ZZv2LK9uadI",
      "id": {
        "kind": "youtube#video",
        "videoId": "CCI0f-r0e7U"
      },
      "snippet": {
        "publishedAt": "2026-03-17T01:45:00Z",
        "channelId": "UCUs_NNRnwTZFxTpQcV_B4Dg",
        "title": "我的乡村生活 #情感家庭纠纷 #农村趣事 #如何处理好家庭关系 #家庭",
        "description": "我的乡村生活 #情感家庭纠纷 #农村趣事 #如何处理好家庭关系 #家庭.",
        "thumbnails": {
          "default": {
            "url": "https://i.ytimg.com/vi/CCI0f-r0e7U/default.jpg",
            "width": 120,
            "height": 90
          },
          "medium": {
            "url": "https://i.ytimg.com/vi/CCI0f-r0e7U/mqdefault.jpg",
            "width": 320,
            "height": 180
          },
          "high": {
            "url": "https://i.ytimg.com/vi/CCI0f-r0e7U/hqdefault.jpg",
            "width": 480,
            "height": 360
          }
        },
        "channelTitle": "糕甜屋",
        "liveBroadcastContent": "none",
        "publishTime": "2026-03-17T01:45:00Z"
      }
    },
    {
      "kind": "youtube#searchResult",
      "etag": "Xqyr9-EjxFkwW_NCID4GosZQd2k",
      "id": {
        "kind": "youtube#video",
        "videoId": "a91fhyyJAW0"
      },
      "snippet": {
        "publishedAt": "2025-11-23T12:00:01Z",
        "channelId": "UCuiqig0xIFhexG73ABx-GbA",
        "title": "一口气看完小说推荐高质量家庭纠纷完结文远离渣男 #一口气系列 #拯救文荒小说 #完结文推荐 #有声小说 #元宝图图",
        "description": "一口气看完小说推荐高质量家庭纠纷完结文远离渣男#一口气系列#拯救文荒小说#完结文推荐#有声小说#元宝图图.",
        "thumbnails": {
          "default": {
            "url": "https://i.ytimg.com/vi/a91fhyyJAW0/default.jpg",
            "width": 120,
            "height": 90
          },
          "medium": {
            "url": "https://i.ytimg.com/vi/a91fhyyJAW0/mqdefault.jpg",
            "width": 320,
            "height": 180
          },
          "high": {
            "url": "https://i.ytimg.com/vi/a91fhyyJAW0/hqdefault.jpg",
            "width": 480,
            "height": 360
          }
        },
        "channelTitle": "元宝图图",
        "liveBroadcastContent": "none",
        "publishTime": "2025-11-23T12:00:01Z"
      }
    },
    {
      "kind": "youtube#searchResult",
      "etag": "h4OvQqF0MtKGPYQfD9AbiDUA_Q0",
      "id": {
        "kind": "youtube#video",
        "videoId": "NZT3saQBnWA"
      },
      "snippet": {
        "publishedAt": "2025-10-23T12:00:47Z",
        "channelId": "UCuiqig0xIFhexG73ABx-GbA",
        "title": "一口气看完爽文小说高质量家庭纠纷完结文推荐 #一口气系列 #拯救文荒小说 #完结文 #有声小说 #元宝图图",
        "description": "一口气看完爽文小说高质量家庭纠纷完结文推荐#一口气系列#拯救文荒小说#完结文#有声小说#元宝图图.",
        "thumbnails": {
          "default": {
            "url": "https://i.ytimg.com/vi/NZT3saQBnWA/default.jpg",
            "width": 120,
            "height": 90
          },
          "medium": {
            "url": "https://i.ytimg.com/vi/NZT3saQBnWA/mqdefault.jpg",
            "width": 320,
            "height": 180
          },
          "high": {
            "url": "https://i.ytimg.com/vi/NZT3saQBnWA/hqdefault.jpg",
            "width": 480,
            "height": 360
          }
        },
        "channelTitle": "元宝图图",
        "liveBroadcastContent": "none",
        "publishTime": "2025-10-23T12:00:47Z"
      }
    },
    {
      "kind": "youtube#searchResult",
      "etag": "vcKnujEQOIQwttaLK_nohIrq2IU",
      "id": {
        "kind": "youtube#video",
        "videoId": "pI2ButobGfI"
      },
      "snippet": {
        "publishedAt": "2026-02-15T12:01:25Z",
        "channelId": "UCuiqig0xIFhexG73ABx-GbA",
        "title": "一口气看完爽文小说推荐家庭纠纷小说完结文 #完结文配享太庙 #一口气系列 #拯救文荒小说推荐 #全文完结一口气看完 #元宝图图",
        "description": "一口气看完爽文小说推荐家庭纠纷小说完结文#完结文配享太庙#一口气系列#拯救文荒小说推荐#全文完结一口气看完#元宝图图.",
        "thumbnails": {
          "default": {
            "url": "https://i.ytimg.com/vi/pI2ButobGfI/default.jpg",
            "width": 120,
            "height": 90
          },
          "medium": {
            "url": "https://i.ytimg.com/vi/pI2ButobGfI/mqdefault.jpg",
            "width": 320,
            "height": 180
          },
          "high": {
            "url": "https://i.ytimg.com/vi/pI2ButobGfI/hqdefault.jpg",
            "width": 480,
            "height": 360
          }
        },
        "channelTitle": "元宝图图",
        "liveBroadcastContent": "none",
        "publishTime": "2026-02-15T12:01:25Z"
      }
    },
    {
      "kind": "youtube#searchResult",
      "etag": "3OCt9WU8MfQbTsfH9ChBj1gW1s4",
      "id": {
        "kind": "youtube#video",
        "videoId": "SmBKBzhj0KA"
      },
      "snippet": {
        "publishedAt": "2026-01-02T12:00:55Z",
        "channelId": "UCuiqig0xIFhexG73ABx-GbA",
        "title": "一口气看完小说推荐高质量家庭纠纷小说推荐老好人的妈妈完结文 #一口气系列 #拯救文荒小说 #完结文 #有声小说 #元宝图图",
        "description": "一口气看完小说推荐高质量家庭纠纷小说推荐老好人的妈妈完结文#一口气系列#拯救文荒小说#完结文#有声小说#元宝图图.",
        "thumbnails": {
          "default": {
            "url": "https://i.ytimg.com/vi/SmBKBzhj0KA/default.jpg",
            "width": 120,
            "height": 90
          },
          "medium": {
            "url": "https://i.ytimg.com/vi/SmBKBzhj0KA/mqdefault.jpg",
            "width": 320,
            "height": 180
          },
          "high": {
            "url": "https://i.ytimg.com/vi/SmBKBzhj0KA/hqdefault.jpg",
            "width": 480,
            "height": 360
          }
        },
        "channelTitle": "元宝图图",
        "liveBroadcastContent": "none",
        "publishTime": "2026-01-02T12:00:55Z"
      }
    },
    {
      "kind": "youtube#searchResult",
      "etag": "iaSLN_Nri2-IVcfZ43foDCLFmlk",
      "id": {
        "kind": "youtube#video",
        "videoId": "5GIXU_2CLPs"
      },
      "snippet": {
        "publishedAt": "2025-10-15T08:00:10Z",
        "channelId": "UC1B1lQEMt-H25hUzEb59OZQ",
        "title": "一口气看完爽文小说推荐高质量家庭纠纷完结文",
        "description": "",
        "thumbnails": {
          "default": {
            "url": "https://i.ytimg.com/vi/5GIXU_2CLPs/default.jpg",
            "width": 120,
            "height": 90
          },
          "medium": {
            "url": "https://i.ytimg.com/vi/5GIXU_2CLPs/mqdefault.jpg",
            "width": 320,
            "height": 180
          },
          "high": {
            "url": "https://i.ytimg.com/vi/5GIXU_2CLPs/hqdefault.jpg",
            "width": 480,
            "height": 360
          }
        },
        "channelTitle": "明月动漫 Moonlight Anime",
        "liveBroadcastContent": "none",
        "publishTime": "2025-10-15T08:00:10Z"
      }
    },
    {
      "kind": "youtube#searchResult",
      "etag": "Xcm2YBwYSm_wVRZbRu13Ighbiwc",
      "id": {
        "kind": "youtube#video",
        "videoId": "nPoVNe31sgg"
      },
      "snippet": {
        "publishedAt": "2025-05-18T15:57:32Z",
        "channelId": "UCR1-y_6dn30fc7X2ijnoP_Q",
        "title": "#欠钱不还#经济纠纷#家庭纠纷#离婚#法务咨询",
        "description": "欠钱不还#经济纠纷#家庭纠纷#离婚#法务咨询.",
        "thumbnails": {
          "default": {
            "url": "https://i.ytimg.com/vi/nPoVNe31sgg/default.jpg",
            "width": 120,
            "height": 90
          },
          "medium": {
            "url": "https://i.ytimg.com/vi/nPoVNe31sgg/mqdefault.jpg",
            "width": 320,
            "height": 180
          },
          "high": {
            "url": "https://i.ytimg.com/vi/nPoVNe31sgg/hqdefault.jpg",
            "width": 480,
            "height": 360
          }
        },
        "channelTitle": "爱说话的老王 ",
        "liveBroadcastContent": "none",
        "publishTime": "2025-05-18T15:57:32Z"
      }
    },
    {
      "kind": "youtube#searchResult",
      "etag": "oTkA7YPvxlc4-XNWr1_tsOwvhN8",
      "id": {
        "kind": "youtube#video",
        "videoId": "zfu8sUbXgfU"
      },
      "snippet": {
        "publishedAt": "2025-10-08T07:56:57Z",
        "channelId": "UCevXE1zfgqp8AXPZIaqndmQ",
        "title": "高质量爽文小说一口气看完家庭纠纷大女主复仇女频文免费看",
        "description": "",
        "thumbnails": {
          "default": {
            "url": "https://i.ytimg.com/vi/zfu8sUbXgfU/default.jpg",
            "width": 120,
            "height": 90
          },
          "medium": {
            "url": "https://i.ytimg.com/vi/zfu8sUbXgfU/mqdefault.jpg",
            "width": 320,
            "height": 180
          },
          "high": {
            "url": "https://i.ytimg.com/vi/zfu8sUbXgfU/hqdefault.jpg",
            "width": 480,
            "height": 360
          }
        },
        "channelTitle": "如烟大帝",
        "liveBroadcastContent": "none",
        "publishTime": "2025-10-08T07:56:57Z"
      }
    },
    {
      "kind": "youtube#searchResult",
      "etag": "jOm1p589I1qxvNVNCfowNpdQSII",
      "id": {
        "kind": "youtube#video",
        "videoId": "XHIQ3j-NVAQ"
      },
      "snippet": {
        "publishedAt": "2025-10-20T08:19:53Z",
        "channelId": "UC1B1lQEMt-H25hUzEb59OZQ",
        "title": "一口气看完爽文小说推荐高质量家庭纠纷完结文",
        "description": "点点订阅，一夜暴富#小说#完结文#动漫#动画.",
        "thumbnails": {
          "default": {
            "url": "https://i.ytimg.com/vi/XHIQ3j-NVAQ/default.jpg",
            "width": 120,
            "height": 90
          },
          "medium": {
            "url": "https://i.ytimg.com/vi/XHIQ3j-NVAQ/mqdefault.jpg",
            "width": 320,
            "height": 180
          },
          "high": {
            "url": "https://i.ytimg.com/vi/XHIQ3j-NVAQ/hqdefault.jpg",
            "width": 480,
            "height": 360
          }
        },
        "channelTitle": "明月动漫 Moonlight Anime",
        "liveBroadcastContent": "none",
        "publishTime": "2025-10-20T08:19:53Z"
      }
    },
    {
      "kind": "youtube#searchResult",
      "etag": "rvNYz0dR3WhDbfYGUOcvxqYRyn4",
      "id": {
        "kind": "youtube#video",
        "videoId": "F3doyV2m910"
      },
      "snippet": {
        "publishedAt": "2025-10-24T03:26:04Z",
        "channelId": "UC1B1lQEMt-H25hUzEb59OZQ",
        "title": "一口气看完爽文小说推荐高质量家庭纠纷完结文",
        "description": "点点订阅，一夜暴富#小说#完结文#动漫#动画.",
        "thumbnails": {
          "default": {
            "url": "https://i.ytimg.com/vi/F3doyV2m910/default.jpg",
            "width": 120,
            "height": 90
          },
          "medium": {
            "url": "https://i.ytimg.com/vi/F3doyV2m910/mqdefault.jpg",
            "width": 320,
            "height": 180
          },
          "high": {
            "url": "https://i.ytimg.com/vi/F3doyV2m910/hqdefault.jpg",
            "width": 480,
            "height": 360
          }
        },
        "channelTitle": "明月动漫 Moonlight Anime",
        "liveBroadcastContent": "none",
        "publishTime": "2025-10-24T03:26:04Z"
      }
    },
    {
      "kind": "youtube#searchResult",
      "etag": "N_AH22yr2ug05erFXJanOZznvEE",
      "id": {
        "kind": "youtube#video",
        "videoId": "-tNXvdHL35c"
      },
      "snippet": {
        "publishedAt": "2026-01-05T12:00:01Z",
        "channelId": "UCuiqig0xIFhexG73ABx-GbA",
        "title": "一口气看完爽文小说推荐高质量家庭纠纷强势的小姑子完结文 #一口气系列 #完结文配享太庙 #拯救文荒小说 #有声小说 #元宝图图",
        "description": "一口气看完爽文小说推荐高质量家庭纠纷强势的小姑子完结文#一口气系列#完结文配享太庙#拯救文荒小说#有声小说#元宝图图.",
        "thumbnails": {
          "default": {
            "url": "https://i.ytimg.com/vi/-tNXvdHL35c/default.jpg",
            "width": 120,
            "height": 90
          },
          "medium": {
            "url": "https://i.ytimg.com/vi/-tNXvdHL35c/mqdefault.jpg",
            "width": 320,
            "height": 180
          },
          "high": {
            "url": "https://i.ytimg.com/vi/-tNXvdHL35c/hqdefault.jpg",
            "width": 480,
            "height": 360
          }
        },
        "channelTitle": "元宝图图",
        "liveBroadcastContent": "none",
        "publishTime": "2026-01-05T12:00:01Z"
      }
    },
    {
      "kind": "youtube#searchResult",
      "etag": "ru2ay0JcCBX5qObOH39U8rrTtJk",
      "id": {
        "kind": "youtube#video",
        "videoId": "4Pub2YhDxL8"
      },
      "snippet": {
        "publishedAt": "2026-03-03T12:00:06Z",
        "channelId": "UCuiqig0xIFhexG73ABx-GbA",
        "title": "一口气看完爽文小说推荐家庭纠纷整治婆婆完结文 #完结文配享太庙 #大女主小说完结文 #完结文一更到底 #拯救文荒小说推荐 #元宝图图",
        "description": "一口气看完爽文小说推荐家庭纠纷整治婆婆完结文#完结文配享太庙#大女主小说完结文#完结文一更到底#拯救文荒小说推荐#元宝图 ...",
        "thumbnails": {
          "default": {
            "url": "https://i.ytimg.com/vi/4Pub2YhDxL8/default.jpg",
            "width": 120,
            "height": 90
          },
          "medium": {
            "url": "https://i.ytimg.com/vi/4Pub2YhDxL8/mqdefault.jpg",
            "width": 320,
            "height": 180
          },
          "high": {
            "url": "https://i.ytimg.com/vi/4Pub2YhDxL8/hqdefault.jpg",
            "width": 480,
            "height": 360
          }
        },
        "channelTitle": "元宝图图",
        "liveBroadcastContent": "none",
        "publishTime": "2026-03-03T12:00:06Z"
      }
    },
    {
      "kind": "youtube#searchResult",
      "etag": "zNKhhHRtyN6s-95Fmup8bLxqQ14",
      "id": {
        "kind": "youtube#video",
        "videoId": "BBqA2fuBlOA"
      },
      "snippet": {
        "publishedAt": "2025-10-27T02:10:55Z",
        "channelId": "UC1B1lQEMt-H25hUzEb59OZQ",
        "title": "一口气看完爽文小说高质量家庭纠纷完结文推荐",
        "description": "点点订阅，一夜暴富#小说#完结文#动漫#动画.",
        "thumbnails": {
          "default": {
            "url": "https://i.ytimg.com/vi/BBqA2fuBlOA/default.jpg",
            "width": 120,
            "height": 90
          },
          "medium": {
            "url": "https://i.ytimg.com/vi/BBqA2fuBlOA/mqdefault.jpg",
            "width": 320,
            "height": 180
          },
          "high": {
            "url": "https://i.ytimg.com/vi/BBqA2fuBlOA/hqdefault.jpg",
            "width": 480,
            "height": 360
          }
        },
        "channelTitle": "明月动漫 Moonlight Anime",
        "liveBroadcastContent": "none",
        "publishTime": "2025-10-27T02:10:55Z"
      }
    },
    {
      "kind": "youtube#searchResult",
      "etag": "c5zt8Ot8AtJEcu8L9IqDPXVWsQc",
      "id": {
        "kind": "youtube#video",
        "videoId": "78sdiFgQ288"
      },
      "snippet": {
        "publishedAt": "2026-01-03T12:00:23Z",
        "channelId": "UCuiqig0xIFhexG73ABx-GbA",
        "title": "一口气看完爽文小说推荐高质量家庭纠纷奇葩妈妈完结文 #完结文配享太庙 #一口气系列 #拯救文荒小说 #有声小说 #元宝图图",
        "description": "一口气看完爽文小说推荐高质量家庭纠纷奇葩妈妈完结文#完结文配享太庙#一口气系列#拯救文荒小说#有声小说#元宝图图.",
        "thumbnails": {
          "default": {
            "url": "https://i.ytimg.com/vi/78sdiFgQ288/default.jpg",
            "width": 120,
            "height": 90
          },
          "medium": {
            "url": "https://i.ytimg.com/vi/78sdiFgQ288/mqdefault.jpg",
            "width": 320,
            "height": 180
          },
          "high": {
            "url": "https://i.ytimg.com/vi/78sdiFgQ288/hqdefault.jpg",
            "width": 480,
            "height": 360
          }
        },
        "channelTitle": "元宝图图",
        "liveBroadcastContent": "none",
        "publishTime": "2026-01-03T12:00:23Z"
      }
    }
  ],
  "nextPageToken": null
}